mlir/execution_engine.py
mlir/ir.py
mlir/passmanager.py
mlir/rewrite.py
mlir/dialects/affine.py
mlir/dialects/amdgpu.py
mlir/dialects/arith.py
mlir/dialects/bufferization.py
mlir/dialects/builtin.py
mlir/dialects/cf.py
mlir/dialects/complex.py
mlir/dialects/emitc.py
mlir/dialects/func.py
mlir/dialects/index.py
mlir/dialects/irdl.py
mlir/dialects/llvm.py
mlir/dialects/math.py
mlir/dialects/memref.py
mlir/dialects/ml_program.py
mlir/dialects/nvgpu.py
mlir/dialects/nvvm.py
mlir/dialects/openacc.py
mlir/dialects/openmp.py
mlir/dialects/pdl.py
mlir/dialects/python_test.py
mlir/dialects/quant.py
mlir/dialects/rocdl.py
mlir/dialects/scf.py
mlir/dialects/shape.py
mlir/dialects/shard.py
mlir/dialects/smt.py
mlir/dialects/sparse_tensor.py
mlir/dialects/spirv.py
mlir/dialects/tensor.py
mlir/dialects/tosa.py
mlir/dialects/ub.py
mlir/dialects/vector.py
mlir/dialects/_acc_ops_gen.py
mlir/dialects/_affine_enum_gen.py
mlir/dialects/_affine_ops_gen.py
mlir/dialects/_amdgpu_enum_gen.py
mlir/dialects/_amdgpu_ops_gen.py
mlir/dialects/_arith_enum_gen.py
mlir/dialects/_arith_ops_gen.py
mlir/dialects/_async_ops_gen.py
mlir/dialects/_bufferization_enum_gen.py
mlir/dialects/_bufferization_ops_gen.py
mlir/dialects/_bufferization_transform_ops_gen.py
mlir/dialects/_builtin_ops_gen.py
mlir/dialects/_cf_ops_gen.py
mlir/dialects/_complex_ops_gen.py
mlir/dialects/_emitc_ops_gen.py
mlir/dialects/_func_ops_gen.py
mlir/dialects/_gpu_enum_gen.py
mlir/dialects/_gpu_ops_gen.py
mlir/dialects/_gpu_transform_ops_gen.py
mlir/dialects/_index_enum_gen.py
mlir/dialects/_index_ops_gen.py
mlir/dialects/_irdl_enum_gen.py
mlir/dialects/_irdl_ops_gen.py
mlir/dialects/_linalg_enum_gen.py
mlir/dialects/_linalg_ops_gen.py
mlir/dialects/_llvm_enum_gen.py
mlir/dialects/_llvm_ops_gen.py
mlir/dialects/_loop_transform_ops_gen.py
mlir/dialects/_math_ops_gen.py
mlir/dialects/_memref_ops_gen.py
mlir/dialects/_memref_transform_ops_gen.py
mlir/dialects/_ml_program_ops_gen.py
mlir/dialects/_nvgpu_enum_gen.py
vgf_adapter_model_explorer-0.4.1.dist-info/DELVEWHEEL
vgf_adapter_model_explorer-0.4.1.dist-info/METADATA
vgf_adapter_model_explorer-0.4.1.dist-info/RECORD
vgf_adapter_model_explorer-0.4.1.dist-info/top_level.txt
vgf_adapter_model_explorer-0.4.1.dist-info/WHEEL
vgf_adapter_model_explorer-0.4.1.dist-info/licenses/LICENSE
