Metadata-Version: 2.4
Name: vgf-adapter-model-explorer
Version: 0.4.1
Summary: Adapter for Model Explorer to support VGF files
License-Expression: Apache-2.0
Project-URL: Repository, https://github.com/arm/vgf-adapter-model-explorer
Project-URL: Changelog, https://github.com/arm/vgf-adapter-model-explorer/releases
Keywords: model-explorer,vgf,visualization
Classifier: Development Status :: 4 - Beta
Classifier: Intended Audience :: Developers
Classifier: Operating System :: POSIX
Classifier: Operating System :: Microsoft :: Windows
Classifier: Operating System :: MacOS
Classifier: Programming Language :: Python :: 3.10
Classifier: Programming Language :: Python :: 3.11
Classifier: Programming Language :: Python :: 3.12
Classifier: Programming Language :: Python :: 3.13
Requires-Python: <3.14,>=3.10
License-File: LICENSE
Requires-Dist: ai-edge-model-explorer<0.2.0,>=0.1.26
Provides-Extra: test
Requires-Dist: pytest; extra == "test"
Requires-Dist: pytest-timeout; extra == "test"
Requires-Dist: ai-edge-model-explorer==0.1.28; extra == "test"
Provides-Extra: format
Requires-Dist: ruff==0.14.2; extra == "format"
Provides-Extra: coverage
Requires-Dist: pytest-cov; extra == "coverage"
Provides-Extra: sbom
Requires-Dist: spdx-tools==0.8.3; extra == "sbom"
Dynamic: license-file
